MANIFEST.in
README.md
main.py
setup.py
UIAutomatorViewer/__init__.py
UIAutomatorViewer/app.py
UIAutomatorViewer/config.py
UIAutomatorViewer/extends.py
UIAutomatorViewer.egg-info/PKG-INFO
UIAutomatorViewer.egg-info/SOURCES.txt
UIAutomatorViewer.egg-info/dependency_links.txt
UIAutomatorViewer.egg-info/entry_points.txt
UIAutomatorViewer.egg-info/requires.txt
UIAutomatorViewer.egg-info/top_level.txt
UIAutomatorViewer/__pycache__/__init__.cpython-39.pyc
UIAutomatorViewer/__pycache__/app.cpython-39.pyc
UIAutomatorViewer/__pycache__/config.cpython-39.pyc
UIAutomatorViewer/__pycache__/extends.cpython-39.pyc
UIAutomatorViewer/api/404.py
UIAutomatorViewer/api/__init__.py
UIAutomatorViewer/api/device.py
UIAutomatorViewer/api/__pycache__/404.cpython-39.pyc
UIAutomatorViewer/api/__pycache__/__init__.cpython-39.pyc
UIAutomatorViewer/api/__pycache__/device.cpython-39.pyc
UIAutomatorViewer/static/ui/index.html
UIAutomatorViewer/static/ui/css/app.0909c81e.css
UIAutomatorViewer/static/ui/css/chunk-vendors.2555329a.css
UIAutomatorViewer/static/ui/fonts/element-icons.f1a45d74.ttf
UIAutomatorViewer/static/ui/fonts/element-icons.ff18efd1.woff
UIAutomatorViewer/static/ui/js/app.e34a7e2b.js
UIAutomatorViewer/static/ui/js/app.e34a7e2b.js.map
UIAutomatorViewer/static/ui/js/chunk-vendors.a132edc1.js
UIAutomatorViewer/static/ui/js/chunk-vendors.a132edc1.js.map
UIAutomatorViewer/static/ui/static/style/scrollbar.css
UIAutomatorViewer/utils/__init__.py
UIAutomatorViewer/utils/response.py
UIAutomatorViewer/utils/__pycache__/__init__.cpython-39.pyc
UIAutomatorViewer/utils/__pycache__/response.cpython-39.pyc