Metadata-Version: 2.1
Name: UIAutomatorViewer
Version: 0.0.4
Summary: 一个基于Python实现的UIAutomatorViewer,比Android原生的UIAutomatorViewer要稳定和方便一些。
Home-page: https://github.com/JingheLee/UIAutomatorViewer.git
Author: Jinghe Lee
Author-email: jinghe_lee@163.com
License: UNKNOWN
Platform: UNKNOWN
